setup.py
Topsis_AnanyaAgarwal_102017085_CS4.egg-info/PKG-INFO
Topsis_AnanyaAgarwal_102017085_CS4.egg-info/SOURCES.txt
Topsis_AnanyaAgarwal_102017085_CS4.egg-info/dependency_links.txt
Topsis_AnanyaAgarwal_102017085_CS4.egg-info/requires.txt
Topsis_AnanyaAgarwal_102017085_CS4.egg-info/top_level.txt
topsis/__init__.py
topsis/ananya_agarwal.py