Metadata-Version: 2.1
Name: Topsis-AnanyaAgarwal-102017085-CS4
Version: 2.0
Summary: Python implementation of the Technique for Order of Preference by Similarity to Ideal Solution (TOPSIS)...
Author: Ananya Agarwal
License: UNKNOWN
Platform: UNKNOWN
